CHANGES.txt
LICENSE
MANIFEST.in
README
setup.py
yaco/__init__.py
yaco.recipe.pycairo.egg-info/PKG-INFO
yaco.recipe.pycairo.egg-info/SOURCES.txt
yaco.recipe.pycairo.egg-info/dependency_links.txt
yaco.recipe.pycairo.egg-info/entry_points.txt
yaco.recipe.pycairo.egg-info/namespace_packages.txt
yaco.recipe.pycairo.egg-info/not-zip-safe
yaco.recipe.pycairo.egg-info/requires.txt
yaco.recipe.pycairo.egg-info/top_level.txt
yaco/recipe/__init__.py
yaco/recipe/pycairo/__init__.py