Metadata-Version: 1.0
Name: yaco.recipe.pycairo
Version: 0.1.1
Summary: Buildout recipe for compiling pycairo
Home-page: http://bitbucket.org/lgs/yaco.recipe.pycairo
Author: Yaco Sistemas (Lorenzo Gil)
Author-email: lgs@yaco.es
License: EUPL
Keywords: pycairo buildout
Platform: UNKNOWN
Classifier: Development Status :: 4 - Beta
Classifier: Framework :: Buildout
